{
  "assetsByChunkName": {
    "vendors~app-account~app-confirmation~app-order": [
      "chunk.8061270a5997e1998862.js",
      "chunk.8061270a5997e1998862.js.map"
    ],
    "vendors~app-account~app-checkout": [
      "chunk.1338ac4c43f6434bd125.js",
      "chunk.1338ac4c43f6434bd125.js.map"
    ],
    "vendors~app-cart~app-checkout": [
      "chunk.fc2388897b54aa5aa3fb.js",
      "chunk.fc2388897b54aa5aa3fb.js.map"
    ],
    "admin": [
      "admin.f6f412481bbae004cf34.js",
      "admin.f6f412481bbae004cf34.js.map"
    ],
    "app-account": [
      "chunk.cf3cfeefea712dd816ce.js",
      "chunk.cf3cfeefea712dd816ce.js.map"
    ],
    "app-cart": [
      "chunk.f3d23e34ae3c12426361.js",
      "chunk.f3d23e34ae3c12426361.js.map"
    ],
    "app-checkout": [
      "chunk.90c70dd8c3ffd927e1c0.js",
      "chunk.90c70dd8c3ffd927e1c0.js.map"
    ],
    "app-confirmation": [
      "chunk.51dc6b2b2b4bb423ffdc.js",
      "chunk.51dc6b2b2b4bb423ffdc.js.map"
    ],
    "app-order": [
      "chunk.d05f9988828db2510347.js",
      "chunk.d05f9988828db2510347.js.map"
    ],
    "checkout": [
      "checkout.7fa163e082fe30ca0f74.js",
      "checkout.7fa163e082fe30ca0f74.js.map"
    ],
    "storefront": [
      "storefront.074a8bfcbd2147673d2b.css",
      "storefront.bb7349dc0d0d01d5a4f7.js",
      "storefront.074a8bfcbd2147673d2b.css.map",
      "storefront.bb7349dc0d0d01d5a4f7.js.map"
    ]
  }
}